nustarpipeline/__init__.py
nustarpipeline/data_manipulation.py
nustarpipeline/get_nustar_data.py
nustarpipeline/plotting.py
nustarpipeline/process.py
nustarpipeline/utils.py
nustarpipeline-0.2.26.dist-info/LICENSE
nustarpipeline-0.2.26.dist-info/METADATA
nustarpipeline-0.2.26.dist-info/WHEEL
nustarpipeline-0.2.26.dist-info/entry_points.txt
nustarpipeline-0.2.26.dist-info/top_level.txt
nustarpipeline-0.2.26.dist-info/RECORD
