Metadata-Version: 2.1
Name: nustarpipeline
Version: 0.2.26
Summary: nustar-pipeline
Home-page: https://gitlab.astro.unige.ch/ferrigno/nustar-pipeline
Author: C.F.
Author-email: carlo.ferrigno@unige.ch
License: MIT
Classifier: Development Status :: 4 - Beta
Classifier: Environment :: Console
Classifier: Intended Audience :: Science/Research
Classifier: License :: OSI Approved :: MIT License
Classifier: Operating System :: POSIX
Classifier: Programming Language :: Python :: 3.6
Classifier: Programming Language :: Python :: 3.7
Classifier: Programming Language :: Python :: 3.8
Classifier: Programming Language :: Python :: 3.9
Classifier: Programming Language :: Python :: 3.10
Classifier: Programming Language :: Python :: 3.11
Classifier: Programming Language :: Python :: 3.12
Classifier: Topic :: Internet
Classifier: Topic :: Scientific/Engineering :: Astronomy
License-File: LICENSE
Requires-Dist: astropy
Requires-Dist: astroquery
Requires-Dist: numpy
Requires-Dist: click
Requires-Dist: argparse
Requires-Dist: matplotlib
Requires-Dist: IPython
Requires-Dist: PyYAML
Requires-Dist: requests
Requires-Dist: bs4
Requires-Dist: lmfit
Requires-Dist: corner
Requires-Dist: stingray
Requires-Dist: emcee
Requires-Dist: cashstatistic
